DigiKala/__init__.py
DigiKala/base.py
DigiKala/search_filter.py
DigiKala/errors/__init__.py
DigiKala/errors/login_error.py
DigiKala/errors/session_error.py
DigiKala/models/__init__.py
DigiKala/models/_cart.py
DigiKala/models/_comment.py
DigiKala/models/_product.py
DigiKala/models/_user.py
DigiKala/models/cart.py
DigiKala/models/color.py
DigiKala/models/comment.py
DigiKala/models/object_model.py
DigiKala/models/product.py
DigiKala/models/question.py
DigiKala/models/search_result.py
DigiKala/models/seller.py
DigiKala/models/user.py
DigiKala-1.0.dist-info/LICENSE
DigiKala-1.0.dist-info/METADATA
DigiKala-1.0.dist-info/WHEEL
DigiKala-1.0.dist-info/top_level.txt
DigiKala-1.0.dist-info/RECORD
