Metadata-Version: 2.1
Name: DigiKala
Version: 1.0
Summary: DigiKala library to connect and work with digikala.com!
Home-page: https://github.com/NuoQte/DigiKala
Author: NuoQTe
Author-email: nuoqte@gmail.com
License: MIT
License-File: LICENSE
Requires-Dist: aiohttp
